pyveritas/__init__.py
pyveritas/contracts.py
pyveritas/rules.py
pyveritas/runner.py
pyveritas/validator.py
pyveritas/examples/test_end_date_after_start_date_rule.py
pyveritas-0.1.17.dist-info/LICENSE
pyveritas-0.1.17.dist-info/WHEEL
pyveritas-0.1.17.dist-info/METADATA
pyveritas-0.1.17.dist-info/RECORD
