Metadata-Version: 2.3
Name: PyVeritas
Version: 0.1.17
Summary: Data Validation Engine
Author-email: Tim McCallum <mistermac2008@gmail.com>
Maintainer-email: Tim McCallum <mistermac2008@gmail.com>
Requires-Python: >=3.7
Classifier: Development Status :: 3 - Alpha
Classifier: Intended Audience :: Developers
Classifier: License :: OSI Approved :: Apache Software License
Classifier: Programming Language :: Python :: 3
Classifier: Programming Language :: Python :: 3.7
Classifier: Programming Language :: Python :: 3.8
Classifier: Programming Language :: Python :: 3.9
Classifier: Programming Language :: Python :: 3.10
Classifier: Topic :: Software Development :: Libraries
Classifier: Topic :: Software Development :: Quality Assurance
Requires-Dist: typing-extensions
Project-URL: Documentation, https://pyveritas.readthedocs.io
Project-URL: Homepage, https://github.com/tpmccallum/PyVeritas
